LGPL-2.1.txt
MANIFEST.in
README.txt
conf.py
index.rst
quickimport.py
quickimport.rst
setup.cfg
setup.py
testQuickimport.py
quickimport.egg-info/PKG-INFO
quickimport.egg-info/SOURCES.txt
quickimport.egg-info/dependency_links.txt
quickimport.egg-info/top_level.txt
quickimport.egg-info/zip-safe