Metadata-Version: 1.0
Name: quickimport
Version: 0.0.1
Summary: Fast imports for rapid application startup
Home-page: http://pypi.python.org/pypi/quickimport
Author: Anselm Kruis
Author-email: a.kruis@science-computing.de
License: GNU Lesser General Public License, version 2.1 or any later version
Keywords: import pep302 performance zipimport
Platform: any
Classifier: License :: OSI Approved :: GNU Library or Lesser General Public License (LGPL)
Classifier: Programming Language :: Python
Classifier: Programming Language :: Python :: 2.7
Classifier: Environment :: Other Environment
Classifier: Operating System :: OS Independent
Classifier: Development Status :: 3 - Alpha
Classifier: Intended Audience :: Developers
Classifier: Topic :: Software Development :: Libraries :: Python Modules
